alibabacloud_pds20220301/__init__.py
alibabacloud_pds20220301/client.py
alibabacloud_pds20220301/models.py
alibabacloud_pds20220301-4.2.6.dist-info/LICENSE
alibabacloud_pds20220301-4.2.6.dist-info/METADATA
alibabacloud_pds20220301-4.2.6.dist-info/WHEEL
alibabacloud_pds20220301-4.2.6.dist-info/top_level.txt
alibabacloud_pds20220301-4.2.6.dist-info/RECORD
